nbvalx/__init__.py
nbvalx/jupyter_magics.py
nbvalx/py.typed
nbvalx/pytest_hooks_notebooks.py
nbvalx/pytest_hooks_unit_tests.py
nbvalx/tempfile.py
nbvalx-0.4.2.dist-info/licenses/AUTHORS
nbvalx-0.4.2.dist-info/licenses/LICENSE
nbvalx-0.4.2.dist-info/METADATA
nbvalx-0.4.2.dist-info/WHEEL
nbvalx-0.4.2.dist-info/top_level.txt
nbvalx-0.4.2.dist-info/RECORD
