Metadata-Version: 2.4
Name: nbvalx
Version: 0.4.2
Summary: Collection of pytest utils built on top of nbval
Author-email: Francesco Ballarin <francesco.ballarin@unicatt.it>
Maintainer-email: Francesco Ballarin <francesco.ballarin@unicatt.it>
License: BSD 3-Clause License
Project-URL: homepage, https://github.com/nbvalx/nbvalx
Project-URL: repository, https://github.com/nbvalx/nbvalx
Project-URL: issues, https://github.com/nbvalx/nbvalx/issues
Project-URL: funding, https://github.com/sponsors/francesco-ballarin
Classifier: Development Status :: 5 - Production/Stable
Classifier: Intended Audience :: Developers
Classifier: Intended Audience :: Science/Research
Classifier: License :: OSI Approved :: BSD License
Classifier: Operating System :: POSIX
Classifier: Operating System :: POSIX :: Linux
Classifier: Operating System :: MacOS :: MacOS X
Classifier: Programming Language :: Python
Classifier: Programming Language :: Python :: 3
Classifier: Programming Language :: Python :: 3.10
Classifier: Programming Language :: Python :: 3.11
Classifier: Programming Language :: Python :: 3.12
Classifier: Programming Language :: Python :: 3.13
Classifier: Programming Language :: Python :: 3.14
Classifier: Topic :: Software Development :: Libraries :: Python Modules
Requires-Python: >=3.10
License-File: LICENSE
License-File: AUTHORS
Requires-Dist: ipython
Requires-Dist: simpleeval
Provides-Extra: unit-tests
Requires-Dist: mpi4py; extra == "unit-tests"
Requires-Dist: pytest>=9.0; extra == "unit-tests"
Provides-Extra: notebooks
Requires-Dist: ipyparallel; extra == "notebooks"
Requires-Dist: mpi4py; extra == "notebooks"
Requires-Dist: nbval; extra == "notebooks"
Requires-Dist: pytest>=9.0; extra == "notebooks"
Provides-Extra: docs
Requires-Dist: sphinx; extra == "docs"
Provides-Extra: lint
Requires-Dist: isort; extra == "lint"
Requires-Dist: mypy; extra == "lint"
Requires-Dist: nbqa; extra == "lint"
Requires-Dist: ruff; extra == "lint"
Requires-Dist: yamllint; extra == "lint"
Provides-Extra: tests
Requires-Dist: coverage[toml]; extra == "tests"
Requires-Dist: pytest>=9.0; extra == "tests"
Dynamic: license-file
